{
    "status": 200,
    "url": "https://images.crunchbase.com/image/upload/c_pad,h_15,f_auto,q_auto:eco,dpr_1/ipqwery/ipqwery_datatable?ik-sanitizeSvg=true",
    "headers": {
        "x-request-id": "08fe6c9f-ea6a-49d8-9d3b-93052d94ddb3",
        "etag": "\"cbe4987604d1413cf61954dd81a5e2f0\"",
        "age": "19859954",
        "access-control-allow-methods": "GET",
        "alt-svc": "h3=\":443\"; ma=86400",
        "x-cache": "Hit from cloudfront",
        "x-amz-cf-id": "EX9ZuFtnLqRS31tqcnqbYzWSXF_j-X-rNJwlQzirGG9OVFPaoZAQtw==",
        "date": "Thu, 23 Oct 2025 18:03:56 GMT",
        "content-type": "image/svg+xml",
        "vary": "Accept",
        "x-server": "ImageKit.io",
        "last-modified": "Sat, 18 Oct 2025 01:24:01 GMT",
        "access-control-allow-headers": "*",
        "cache-control": "public, s-maxage=31536000, max-age=31536000, must-revalidate",
        "timing-allow-origin": "*",
        "via": "1.1 3998ee43a990bae5d9a82ad1c8c4f910.cloudfront.net (CloudFront)",
        "access-control-allow-origin": "*",
        "content-length": "5554",
        "x-amz-cf-pop": "VIE50-P4"
    },
    "timing": {
        "startTime": 1781102590252.648,
        "domainLookupStart": -1,
        "domainLookupEnd": -1,
        "connectStart": -1,
        "secureConnectionStart": -1,
        "connectEnd": -1,
        "requestStart": 0.827,
        "responseStart": 9.7,
        "responseEnd": -1
    }
}